python_hotkeys/__init__.py
python_hotkeys-0.1.1.dist-info/licenses/LICENSE
python_hotkeys-0.1.1.dist-info/METADATA
python_hotkeys-0.1.1.dist-info/WHEEL
python_hotkeys-0.1.1.dist-info/entry_points.txt
python_hotkeys-0.1.1.dist-info/top_level.txt
python_hotkeys-0.1.1.dist-info/RECORD
