Metadata-Version: 2.4
Name: python-hotkeys
Version: 0.1.1
Summary: A robust, single-file, dependency-free library for capturing global terminal hotkeys on Unix-like systems, with support for both sync and async callbacks.
Author-email: "Mauro D. Sauco" <mauro@sauco.net>
License: MIT License
Project-URL: Homepage, https://github.com/transparentlyai/python-hotkeys
Project-URL: Issues, https://github.com/transparentlyai/python-hotkeys/issues
Keywords: hotkey,terminal,keyboard,asyncio,tui,shortcut
Classifier: Development Status :: 4 - Beta
Classifier: Intended Audience :: Developers
Classifier: License :: OSI Approved :: MIT License
Classifier: Operating System :: MacOS
Classifier: Operating System :: POSIX :: Linux
Classifier: Programming Language :: Python :: 3
Classifier: Programming Language :: Python :: 3.7
Classifier: Programming Language :: Python :: 3.8
Classifier: Programming Language :: Python :: 3.9
Classifier: Programming Language :: Python :: 3.10
Classifier: Programming Language :: Python :: 3.11
Classifier: Programming Language :: Python :: 3.12
Classifier: Topic :: Terminals
Classifier: Topic :: Software Development :: Libraries :: Python Modules
Requires-Python: >=3.7
License-File: LICENSE
Dynamic: license-file
